azpaddypy/__init__.py
azpaddypy/builder/__init__.py
azpaddypy/builder/configuration.py
azpaddypy/builder/directors.py
azpaddypy/mcp/__init__.py
azpaddypy/mcp/__main__.py
azpaddypy/mcp/azure_mcp_server.py
azpaddypy/mcp/services/__init__.py
azpaddypy/mcp/services/aiagents.py
azpaddypy/mcp/services/base.py
azpaddypy/mcp/services/cosmos.py
azpaddypy/mcp/services/resources.py
azpaddypy/mcp/services/storage.py
azpaddypy/mcp/services/subscription.py
azpaddypy/mgmt/__init__.py
azpaddypy/mgmt/identity.py
azpaddypy/mgmt/local_env_manager.py
azpaddypy/mgmt/logging.py
azpaddypy/resources/__init__.py
azpaddypy/resources/_utils.py
azpaddypy/resources/cosmosdb.py
azpaddypy/resources/keyvault.py
azpaddypy/resources/storage.py
azpaddypy/tools/__init__.py
azpaddypy/tools/configuration_manager.py
azpaddypy/tools/cosmos_prompt_manager.py
azpaddypy/tools/prompt_models.py
azpaddypy-0.9.72.dist-info/licenses/LICENSE
azpaddypy-0.9.72.dist-info/METADATA
azpaddypy-0.9.72.dist-info/WHEEL
azpaddypy-0.9.72.dist-info/top_level.txt
azpaddypy-0.9.72.dist-info/RECORD
