Metadata-Version: 2.4
Name: azpaddypy
Version: 0.9.72
Summary: Comprehensive Python logger for Azure, integrating OpenTelemetry for advanced, structured, and distributed tracing.
Classifier: Programming Language :: Python :: 3
Classifier: Operating System :: OS Independent
Requires-Python: <3.12,>=3.11.10
License-File: LICENSE
Requires-Dist: azure-monitor-opentelemetry==1.6.10
Requires-Dist: azure-identity==1.23.0
Requires-Dist: azure-keyvault-secrets==4.10.0
Requires-Dist: azure-keyvault-keys==4.11.0
Requires-Dist: azure-keyvault-certificates==4.10.0
Requires-Dist: azure-storage-blob==12.25.1
Requires-Dist: azure-storage-file-share==12.21.0
Requires-Dist: azure-storage-queue==12.12.0
Requires-Dist: azure-cosmos==4.9.0
Requires-Dist: chardet==5.2.0
Requires-Dist: fastmcp==2.12.4
Requires-Dist: azure-mgmt-resource==24.0.0
Requires-Dist: azure-mgmt-storage==23.1.0
Requires-Dist: azure-mgmt-cosmosdb==9.8.0
Requires-Dist: azure-functions==1.22.1
Requires-Dist: azure-ai-projects==1.0.0
Requires-Dist: pytest==8.4.2
Provides-Extra: dev
Requires-Dist: azure-cosmos==4.9.0; extra == "dev"
Requires-Dist: pytest==8.4.2; extra == "dev"
Requires-Dist: pytest-cov==7.0.0; extra == "dev"
Requires-Dist: pytest-asyncio==1.2.0; extra == "dev"
Requires-Dist: anyio==4.9.0; extra == "dev"
Requires-Dist: jupyter==1.1.1; extra == "dev"
Requires-Dist: ipykernel==7.0.1; extra == "dev"
Requires-Dist: pytest-profiling==1.7.0; extra == "dev"
Dynamic: license-file
